geo_convert_util/__init__.py
geo_convert_util/conversion.py
geo_convert_util-0.0.1.dist-info/LICENSE
geo_convert_util-0.0.1.dist-info/METADATA
geo_convert_util-0.0.1.dist-info/WHEEL
geo_convert_util-0.0.1.dist-info/top_level.txt
geo_convert_util-0.0.1.dist-info/RECORD
