Metadata-Version: 2.2
Name: geo_convert_util
Version: 0.0.1
Summary: Conversões de áreas
Home-page: https://github.com/paulosergiocf/geoutil
Author: paulosergiocf
Author-email: paulosergiocf.dev@gmail.com
Classifier: Programming Language :: Python :: 3
Classifier: License :: OSI Approved :: MIT License
Classifier: Operating System :: OS Independent
Requires-Python: >=3.7
License-File: LICENSE
Dynamic: author
Dynamic: author-email
Dynamic: classifier
Dynamic: description
Dynamic: description-content-type
Dynamic: home-page
Dynamic: requires-python
Dynamic: summary
